rawsocketpy/__init__.py
rawsocketpy/asyncserver.py
rawsocketpy/main.py
rawsocketpy/packet.py
rawsocketpy/server.py
rawsocketpy/socket.py
rawsocketpy/util.py
rawsocketpy-0.3.0.dist-info/METADATA
rawsocketpy-0.3.0.dist-info/RECORD
rawsocketpy-0.3.0.dist-info/WHEEL
rawsocketpy-0.3.0.dist-info/top_level.txt
