Metadata-Version: 2.1
Name: rawsocketpy
Version: 0.3.0
Summary: This library allows you to implement a custom layer 2 communication using raw sockets in Python 2 and Python 3, synchronous and asynchronous, with and without callbacks.
Home-page: https://github.com/AlexisTM/rawsocket_python
Author: AlexisTM
Author-email: alexis.paques@gmail.com
License: MIT
Platform: UNKNOWN
Classifier: Programming Language :: Python :: 2
Classifier: Programming Language :: Python :: 2
Classifier: Development Status :: 4 - Beta
Classifier: License :: OSI Approved :: MIT License
Classifier: Operating System :: POSIX :: Linux
Classifier: Topic :: Internet
Classifier: Topic :: System :: Networking
Classifier: Topic :: System :: Networking :: Monitoring
